Metadata-Version: 2.1
Name: assetx
Version: 1.0
Summary: asset manager.
Author: helper
License: MIT
Keywords: style
Classifier: Development Status :: 5 - Production/Stable
